nonebot_plugin_itreflection/__init__.py
nonebot_plugin_itreflection/config.py
nonebot_plugin_itreflection/data_source.py
nonebot_plugin_itreflection-0.0.1.dist-info/METADATA
nonebot_plugin_itreflection-0.0.1.dist-info/WHEEL
nonebot_plugin_itreflection-0.0.1.dist-info/top_level.txt
nonebot_plugin_itreflection-0.0.1.dist-info/RECORD
