Metadata-Version: 2.1
Name: nonebot-plugin-itreflection
Version: 0.0.1
Summary: 适用于nonebot2的交互式反射插件
Home-page: https://github.com/maxesisn/nonebot_plugin_itreflection
Author: maxesisn
Author-email: me@maxesisn.online
License: UNKNOWN
Platform: UNKNOWN
Classifier: Framework :: AsyncIO
Classifier: Operating System :: OS Independent
Classifier: License :: OSI Approved :: GNU General Public License v3 (GPLv3)
Classifier: Programming Language :: Python
Classifier: Programming Language :: Python :: 3.8
